geoguessr_api/__init__.py
geoguessr_api/geo_errors.py
geoguessr_api/geo_utils.py
geoguessr_api/geoguessr.py
geoguessr_api/models.py
api_geoguessr-1.0.0.dist-info/METADATA
api_geoguessr-1.0.0.dist-info/WHEEL
api_geoguessr-1.0.0.dist-info/licenses/LICENSE
api_geoguessr-1.0.0.dist-info/RECORD
