Metadata-Version: 2.1
Name: api-geoguessr
Version: 1.0.0
Summary: An asynchronous API integrator for Geoguessr
Project-URL: Homepage, https://github.com/toinoublz/geoguessr-api
Author-email: Antoine BLAISE <antoine.blaise34@gmail.com>
License-File: LICENSE
Classifier: License :: OSI Approved :: MIT License
Classifier: Operating System :: OS Independent
Classifier: Programming Language :: Python :: 3
Requires-Python: >=3.9
Requires-Dist: requests>=2.26.0
